listfmt.py
list_fmt-0.0.1.dist-info/METADATA
list_fmt-0.0.1.dist-info/WHEEL
list_fmt-0.0.1.dist-info/top_level.txt
list_fmt-0.0.1.dist-info/RECORD
