Metadata-Version: 2.1
Name: list-fmt
Version: 0.0.1
Summary: Format Iterables
License: MIT
Project-URL: Repository, https://github.com/phoenixr-codes/list-fmt/
Project-URL: Documentation, https://phoenixr-codes.github.io/list-fmt/
Keywords: Formatting,Human,Iterable,List
Classifier: Development Status :: 4 - Beta
Classifier: Typing :: Typed
Requires-Python: >=3.7
Requires-Dist: b26
Requires-Dist: roman
Provides-Extra: docs
Requires-Dist: furo ; extra == 'docs'
Requires-Dist: matplotlib ; extra == 'docs'
Requires-Dist: Sphinx ; extra == 'docs'
Requires-Dist: sphinx-copybutton ; extra == 'docs'
Requires-Dist: sphinxcontrib-repl ; extra == 'docs'
Requires-Dist: sphinxcontrib-trio ; extra == 'docs'
